LICENSE.txt
MANIFEST.in
README.md
requirements.txt
setup.cfg
setup.py
falconjsonio/__init__.py
falconjsonio/middleware.py
falconjsonio/schema.py
falconjsonio/test.py
falconjsonio.egg-info/PKG-INFO
falconjsonio.egg-info/SOURCES.txt
falconjsonio.egg-info/dependency_links.txt
falconjsonio.egg-info/not-zip-safe
falconjsonio.egg-info/requires.txt
falconjsonio.egg-info/top_level.txt