Metadata-Version: 1.1
Name: falconjsonio
Version: 0.1.6
Summary: JSON-Schema input and output for Falcon
Home-page: https://bitbucket.org/garymonson/falcon-json-io
Author: Gary Monson
Author-email: gary.monson@gmail.com
License: MIT
Keywords: json schema falcon
Platform: UNKNOWN
Classifier: Development Status :: 3 - Alpha
Classifier: Intended Audience :: Developers
Classifier: Topic :: Internet :: WWW/HTTP :: WSGI :: Middleware
Classifier: Topic :: Software Development :: Libraries :: Python Modules
Classifier: License :: OSI Approved :: MIT License
Classifier: Programming Language :: Python :: 3
Classifier: Programming Language :: Python :: 3.4
